aprslib/IS.py
aprslib/__init__.py
aprslib/base91.py
aprslib/exceptions.py
aprslib/inet.py
aprslib/parsing.py
aprslib/passcode.py
aprslib/packets/__init__.py
aprslib/packets/base.py
aprslib/packets/position.py
aprslib/packets/telemetry.py
aprslib/parsing/__init__.py
aprslib/parsing/common.py
aprslib/parsing/message.py
aprslib/parsing/mice.py
aprslib/parsing/misc.py
aprslib/parsing/position.py
aprslib/parsing/telemetry.py
aprslib/parsing/thirdparty.py
aprslib/parsing/weather.py
aprslib/util/__init__.py
aprslib-0.7.1.dist-info/LICENSE
aprslib-0.7.1.dist-info/METADATA
aprslib-0.7.1.dist-info/WHEEL
aprslib-0.7.1.dist-info/pbr.json
aprslib-0.7.1.dist-info/top_level.txt
aprslib-0.7.1.dist-info/zip-safe
aprslib-0.7.1.dist-info/RECORD
