Metadata-Version: 2.1
Name: aprslib
Version: 0.7.1
Summary: Module for accessing APRS-IS and parsing APRS packets
Home-page: https://github.com/rossengeorgiev/aprs-python
Author: Rossen Georgiev
Author-email: hello@rgp.io
License: GPLv2
Keywords: aprs aprslib parse parsing aprs-is library base91
Platform: UNKNOWN
Classifier: Development Status :: 4 - Beta
Classifier: Intended Audience :: Developers
Classifier: License :: OSI Approved :: GNU General Public License v2 (GPLv2)
Classifier: Programming Language :: Python
Classifier: Programming Language :: Python :: 2
Classifier: Programming Language :: Python :: 3
Classifier: Programming Language :: Python :: Implementation :: PyPy
Classifier: Topic :: Communications :: Ham Radio
